[
  {
    "name": "Opo Light",
    "background": "#fbf8f2",
    "foreground": "#24292f",
    "cursorColor": "#005ccc",
    "selectionBackground": "#eeeae2",
    "black": "#24292f",
    "red": "#9e4600",
    "green": "#005d3f",
    "yellow": "#925c00",
    "blue": "#005ccc",
    "purple": "#7b3c79",
    "cyan": "#00635f",
    "white": "#eeeae2",
    "brightBlack": "#57606a",
    "brightRed": "#e08440",
    "brightGreen": "#419977",
    "brightYellow": "#dca331",
    "brightBlue": "#478df5",
    "brightPurple": "#ad6aab",
    "brightCyan": "#209993",
    "brightWhite": "#ffffff"
  },
  {
    "name": "Opo Dark",
    "background": "#161410",
    "foreground": "#d1d7df",
    "cursorColor": "#3384f7",
    "selectionBackground": "#1c1a14",
    "black": "#57606a",
    "red": "#e08440",
    "green": "#419977",
    "yellow": "#dca331",
    "blue": "#478df5",
    "purple": "#ad6aab",
    "cyan": "#209993",
    "white": "#ffffff",
    "brightBlack": "#79838d",
    "brightRed": "#ffaf7a",
    "brightGreen": "#68bf9b",
    "brightYellow": "#ffcb70",
    "brightBlue": "#84b6ff",
    "brightPurple": "#d48fd1",
    "brightCyan": "#52bfb9",
    "brightWhite": "#ffffff"
  },
  {
    "name": "Opo High Contrast",
    "background": "#fdfaf3",
    "foreground": "#13191f",
    "cursorColor": "#003c88",
    "selectionBackground": "#f4efe5",
    "black": "#13191f",
    "red": "#663000",
    "green": "#003c29",
    "yellow": "#5b3f00",
    "blue": "#003c88",
    "purple": "#5c125c",
    "cyan": "#003e3c",
    "white": "#a39f96",
    "brightBlack": "#727d89",
    "brightRed": "#ffa568",
    "brightGreen": "#53bb93",
    "brightYellow": "#ffc251",
    "brightBlue": "#79afff",
    "brightPurple": "#d384d0",
    "brightCyan": "#2dbbb4",
    "brightWhite": "#ffffff"
  }
]
